MANIFEST.in
README.md
dev-requirements.txt
requirements.txt
setup.py
munibot/__init__.py
munibot/config.py
munibot/image.py
munibot/munibot.py
munibot/tweet.py
munibot.egg-info/PKG-INFO
munibot.egg-info/SOURCES.txt
munibot.egg-info/dependency_links.txt
munibot.egg-info/entry_points.txt
munibot.egg-info/requires.txt
munibot.egg-info/top_level.txt
munibot/profiles/__init__.py
munibot/profiles/base.py