Metadata-Version: 2.1
Name: munibot
Version: 0.0.3
Summary: A Twitter bot that tweets aerial imagery pictures of municipalities
Home-page: https://github.com/amercader/munibot
Author: Adrià Mercader
Author-email: amercadero@gmail.com
License: UNKNOWN
Platform: UNKNOWN
Classifier: Programming Language :: Python :: 3
Classifier: License :: OSI Approved :: MIT License
Classifier: Operating System :: OS Independent
Requires-Python: >=3.6
